binproto2/__init__.py
binproto2/exceptions.py
binproto2/protocols.py
marlin_binary_protocol-0.0.7.dist-info/LICENSE
marlin_binary_protocol-0.0.7.dist-info/METADATA
marlin_binary_protocol-0.0.7.dist-info/WHEEL
marlin_binary_protocol-0.0.7.dist-info/top_level.txt
marlin_binary_protocol-0.0.7.dist-info/RECORD
