Metadata-Version: 2.1
Name: marlin-binary-protocol
Version: 0.0.7
Summary: Transfer files with Marlin 2.0 firmware using Marlin Binary Protocol Mark II
Home-page: https://github.com/charleswillis3/marlin-binary-protocol
Author: Charles Willis
Author-email: charleswillis3@users.noreply.github.com
License: UNKNOWN
Platform: UNKNOWN
Classifier: Programming Language :: Python :: 2.7
Classifier: Programming Language :: Python :: 3
Classifier: License :: OSI Approved :: MIT License
Classifier: Operating System :: OS Independent
Requires-Python: >=2.6, !=3.0.*, !=3.1.*, !=3.2.*, !=3.3.*, !=3.4.*, <4
Requires-Dist: heatshrink (>=0.3.2)
Requires-Dist: heatshrink2 (>=0.9)
Requires-Dist: pyserial (>=3.4)
Requires-Dist: backports.time-perf-counter ; python_version < "3.3"
